edds/__init__.py
edds/edds.py
edds-1.3.2.dist-info/LICENSE
edds-1.3.2.dist-info/METADATA
edds-1.3.2.dist-info/WHEEL
edds-1.3.2.dist-info/top_level.txt
edds-1.3.2.dist-info/RECORD
