Metadata-Version: 2.1
Name: edds
Version: 1.3.2
Summary: The Central Bank of the Republic of Türkiye Electronic Data Distribution System Data Access Package
Home-page: https://github.com/altanalaybeyoglu/edds
Author: Altan Alaybeyoğlu
Author-email: altanalaybeyoglu@gmail.com
Classifier: Programming Language :: Python :: 3
Classifier: License :: OSI Approved :: MIT License
Classifier: Operating System :: OS Independent
License-File: LICENSE
Requires-Dist: requests
Requires-Dist: pandas
